tests/__init__.py
tests/test_my_tool.py
yao_test_package1/__init__.py
yao_test_package1/tools/__init__.py
yao_test_package1/tools/my_tool.py
yao_test_package1/tools/utils.py
yao_test_package1/yamls/my_tool.yaml
yao_test_package1-0.0.1.dist-info/METADATA
yao_test_package1-0.0.1.dist-info/WHEEL
yao_test_package1-0.0.1.dist-info/entry_points.txt
yao_test_package1-0.0.1.dist-info/top_level.txt
yao_test_package1-0.0.1.dist-info/RECORD
