Metadata-Version: 2.1
Name: yao-test-package1
Version: 0.0.1
Summary: This is my tools package
